pangeo_forge_runner/__init__.py
pangeo_forge_runner/_version.py
pangeo_forge_runner/cli.py
pangeo_forge_runner/dtypes.py
pangeo_forge_runner/feedstock.py
pangeo_forge_runner/meta_yaml.py
pangeo_forge_runner/plugin.py
pangeo_forge_runner/recipe_rewriter.py
pangeo_forge_runner/storage.py
pangeo_forge_runner/stream_capture.py
pangeo_forge_runner/bakery/__init__.py
pangeo_forge_runner/bakery/base.py
pangeo_forge_runner/bakery/dataflow.py
pangeo_forge_runner/bakery/flink.py
pangeo_forge_runner/bakery/local.py
pangeo_forge_runner/commands/__init__.py
pangeo_forge_runner/commands/bake.py
pangeo_forge_runner/commands/base.py
pangeo_forge_runner/commands/expand_meta.py
pangeo_forge_runner-0.10.2.dist-info/LICENSE
pangeo_forge_runner-0.10.2.dist-info/METADATA
pangeo_forge_runner-0.10.2.dist-info/WHEEL
pangeo_forge_runner-0.10.2.dist-info/entry_points.txt
pangeo_forge_runner-0.10.2.dist-info/top_level.txt
pangeo_forge_runner-0.10.2.dist-info/RECORD
