Metadata-Version: 2.1
Name: pangeo-forge-runner
Version: 0.10.2
Summary: Commandline tool to manage pangeo-forge feedstocks
Author-email: Yuvi Panda <yuvipanda@gmail.com>
License: Apache-2.0
Project-URL: Homepage, https://github.com/pangeo-forge/pangeo-forge-runner
Project-URL: Tracker, https://github.com/pangeo-forge/pangeo-forge-runner/issues
Project-URL: Documentation, https://pangeo-forge-runner.readthedocs.io/en/latest/
Keywords: pangeo,data
Classifier: Development Status :: 1 - Planning
Classifier: License :: OSI Approved :: Apache Software License
Classifier: Operating System :: OS Independent
Classifier: Intended Audience :: Science/Research
Classifier: Programming Language :: Python
Classifier: Programming Language :: Python :: 3
Classifier: Programming Language :: Python :: 3.8
Classifier: Programming Language :: Python :: 3.9
Classifier: Topic :: Scientific/Engineering
Requires-Python: >=3.9
License-File: LICENSE
Requires-Dist: escapism
Requires-Dist: importlib-metadata
Requires-Dist: jsonschema
Requires-Dist: jupyter-repo2docker
Requires-Dist: ruamel.yaml
Requires-Dist: traitlets
Requires-Dist: venvception >=0.0.5
Requires-Dist: fsspec
Provides-Extra: test
Requires-Dist: pytest ; extra == 'test'
Requires-Dist: pytest-cov ; extra == 'test'
Requires-Dist: pytest-mock ; extra == 'test'
Requires-Dist: gcsfs ; extra == 'test'
Requires-Dist: s3fs ; extra == 'test'
Requires-Dist: apache-beam ; extra == 'test'
Requires-Dist: zarr ; extra == 'test'
Requires-Dist: xarray ; extra == 'test'
